tjrcr/__init__.py
tjrcr/tjrcr.py
tjrcr-2.0.0.dist-info/METADATA
tjrcr-2.0.0.dist-info/WHEEL
tjrcr-2.0.0.dist-info/RECORD
