Metadata-Version: 2.1
Name: tjrcr
Version: 2.0.0
Summary: Library for validating parameters for comprehensive reservoir regulation.
Home-page: https://github.com/duynguyen02/tjrcr
Author: Duy Nguyen
Author-email: duynguyen02.dev@gmail.com
Requires-Python: >=3.9,<4.0
Classifier: Programming Language :: Python :: 3
Classifier: Programming Language :: Python :: 3.9
Classifier: Programming Language :: Python :: 3.10
Classifier: Programming Language :: Python :: 3.11
Classifier: Programming Language :: Python :: 3.12
Requires-Dist: pandas (>=2.2.2,<3.0.0)
Requires-Dist: tjwb (>=2.1.0,<3.0.0)
Project-URL: Repository, https://github.com/duynguyen02/tjrcr
